fiap_valteci/__init__.py
fiap_valteci/core.py
fiap_valteci_package-1.0.0.dist-info/METADATA
fiap_valteci_package-1.0.0.dist-info/WHEEL
fiap_valteci_package-1.0.0.dist-info/top_level.txt
fiap_valteci_package-1.0.0.dist-info/RECORD
