Metadata-Version: 2.1
Name: fiap_valteci-package
Version: 1.0.0
Summary: Descricao da sua lib fiap_valteci
Home-page: https://github.com/valteci/
Author: valteci
Author-email: valtecijunior@gmail.com
License: MIT
